{
  "date": "2026-03-10",
  "hebrew_date": "י״א אדר תשפ״ו",
  "literary_events": [
    {
      "title": "יום הולדתו של אלכסנדר פן",
      "description": "המשורר העברי אלכסנדר פן, מגדולי המשוררים הארצישראליים, נולד ב-1906 ברוסיה.",
      "type": "israeli",
      "year": 1906
    }
  ],
  "post_suggestions": [
    {
      "title": "לציון יום הולדתו של אלכסנדר פן",
      "description": "פוסט לכבוד יום הולדתו של אלכסנדר פן. המשורר העברי אלכסנדר פן, מגדולי המשוררים הארצישראליים, נולד ב-1906 ברוסיה. ניתן לשתף ציטוט מיצירותיו/ה ולהזמין את הקוראים להגיב עם היצירה האהובה עליהם.",
      "hashtags": [
        "#ספריותתלאביב",
        "#ספרות_עברית",
        "#היום_בהיסטוריה"
      ]
    },
    {
      "title": "אביב, פרחים וספרים",
      "description": "האביב הגיע! המלצות לקריאת אביב — ספרים קלילים, שירה, וספרי טבע. בואו לקרוא בגינת הספרייה.",
      "hashtags": [
        "#ספריותתלאביב",
        "#קריאת_אביב",
        "#ספרים_וטבע"
      ]
    },
    {
      "title": "הספר שמחכה לכם על המדף",
      "description": "פוסט עם תמונה של מדף ספרים מסניף הספרייה — 'באו לגלות מה מחכה לכם היום'. הזמנה חמה לביקור בספרייה הקרובה.",
      "hashtags": [
        "#ספריותתלאביב",
        "#בואו_לספרייה",
        "#קריאה_מהנה"
      ]
    }
  ]
}