{
  "date": "2026-03-16",
  "hebrew_date": "כ״ה אדר תשפ״ו",
  "literary_events": [
    {
      "title": "פטירתו של עגנון — חודש פטירתו",
      "description": "ש״י עגנון, זוכה פרס נובל לספרות, נפטר ב-17 בפברואר 1970 בירושלים.",
      "type": "israeli",
      "year": 1970
    }
  ],
  "post_suggestions": [
    {
      "title": "לציון פטירתו של עגנון — חודש פטירתו",
      "description": "פוסט לכבוד פטירתו של עגנון — חודש פטירתו. ש״י עגנון, זוכה פרס נובל לספרות, נפטר ב-17 בפברואר 1970 בירושלים. ניתן לשתף ציטוט מיצירותיו/ה ולהזמין את הקוראים להגיב עם היצירה האהובה עליהם.",
      "hashtags": [
        "#ספריותתלאביב",
        "#ספרות_עברית",
        "#היום_בהיסטוריה"
      ]
    },
    {
      "title": "אביב, פרחים וספרים",
      "description": "האביב הגיע! המלצות לקריאת אביב — ספרים קלילים, שירה, וספרי טבע. בואו לקרוא בגינת הספרייה.",
      "hashtags": [
        "#ספריותתלאביב",
        "#קריאת_אביב",
        "#ספרים_וטבע"
      ]
    },
    {
      "title": "הספר שמחכה לכם על המדף",
      "description": "פוסט עם תמונה של מדף ספרים מסניף הספרייה — 'באו לגלות מה מחכה לכם היום'. הזמנה חמה לביקור בספרייה הקרובה.",
      "hashtags": [
        "#ספריותתלאביב",
        "#בואו_לספרייה",
        "#קריאה_מהנה"
      ]
    }
  ]
}