{
  "date": "2026-12-06",
  "hebrew_date": "י״ח כסלו תשפ״ז",
  "literary_events": [
    {
      "title": "יום הולדתה של שרלוט בירסטון",
      "description": "הסופרת הישראלית-אמריקאית שחיה ותרמה לספרות העברית.",
      "type": "israeli"
    }
  ],
  "post_suggestions": [
    {
      "title": "לציון יום הולדתה של שרלוט בירסטון",
      "description": "פוסט לכבוד יום הולדתה של שרלוט בירסטון. הסופרת הישראלית-אמריקאית שחיה ותרמה לספרות העברית. ניתן לשתף ציטוט מיצירותיו/ה ולהזמין את הקוראים להגיב עם היצירה האהובה עליהם.",
      "hashtags": [
        "#ספריותתלאביב",
        "#ספרות_עברית",
        "#היום_בהיסטוריה"
      ]
    },
    {
      "title": "סיכום שנת קריאה",
      "description": "מה הספר הכי טוב שקראתם השנה? שתפו את ההמלצות שלכם ובואו ליצור רשימת 'הטובים ביותר' של הקהילה.",
      "hashtags": [
        "#ספריותתלאביב",
        "#סיכום_שנתי",
        "#הספר_של_השנה"
      ]
    },
    {
      "title": "הספר שמחכה לכם על המדף",
      "description": "פוסט עם תמונה של מדף ספרים מסניף הספרייה — 'באו לגלות מה מחכה לכם היום'. הזמנה חמה לביקור בספרייה הקרובה.",
      "hashtags": [
        "#ספריותתלאביב",
        "#בואו_לספרייה",
        "#קריאה_מהנה"
      ]
    }
  ]
}